[
    {
        "name": "",
        "source": "",
        "alter": {
            "summary": {
                "replace": "",
                "prepend": "",
                "append": ""
            },
            "description": {
                "replace": "",
                "prepend": "",
                "append": ""
            },
            "location": {
                "replace": "",
                "prepend": "",
                "append": ""
            }
        },
        "include":{
            "summary": {
                "contains": "",
                "regex": "",
                "equals": ""
            },
            "description": {
                "contains": "",
                "regex": "",
                "equals": ""
            },
            "location": {
                "contains": "",
                "regex": "",
                "equals": ""
            }
        },
        "exclude":{
            "summary": {
                "contains": "",
                "regex": "",
                "equals": ""
            },
            "description": {
                "contains": "",
                "regex": "",
                "equals": ""
            },
            "location": {
                "contains": "",
                "regex": "",
                "equals": ""
            }
        },
        "datestamp": {
            "dateformat": "%Y-%m-%d %H:%M:%S",
            "stamptemplate": "Event last fetched from origin: [[date]]",
            "stampposition": "prepend"
        }
    },
    {
        "name": "",
        "source": "",
        "alter": {
            "summary": {
                "replace": "",
                "prepend": "",
                "append": ""
            },
            "description": {
                "replace": "",
                "prepend": "",
                "append": ""
            },
            "location": {
                "replace": "",
                "prepend": "",
                "append": ""
            }
        },
        "include":{
            "summary": {
                "contains": "",
                "regex": "",
                "equals": ""
            },
            "description": {
                "contains": "",
                "regex": "",
                "equals": ""
            },
            "location": {
                "contains": "",
                "regex": "",
                "equals": ""
            }
        }
    }
]